[
    {
        "id": "header_1",
        "type": "color",
        "label": "Color link Top Header",
        "selector": ".bottomnav a,.bottomnav .popup-over .popup-title,.bottomnav .popup-over.popup-white .popup-title,.bottomnav .popup-over.popup-white.light .popup-title"
    },
    {
        "id": "header_2",
        "type": "color",
        "label": "Color link hover Top Header",
        "media": "@media (min-width: 992px)",
        "selector": ".bottomnav a:hover,.bottomnav .popup-over .popup-title:hover,.bottomnav .popup-over.popup-white .popup-title:hover,.bottomnav .popup-over.popup-white.light .popup-title:hover"
    },
    {
        "id": "header_3",
        "type": "background-color",
        "label": "Background Color Top Header",
        "selector": ".bottomnav"
    },
    {
        "id": "header_4",
        "type": "background-color",
        "label": "Background color Bottom Header",
        "responsive": [
            {
                "media": "@media (min-width: 992px)",
                "selector": ".sticky-menu-active .header-top"
            }
        ],
        "selector": ".header-top"
    },
    {
        "id": "header_5",
        "type": "color",
        "label": "Color Cart",
        "selector": "#cart-block .cart-preview, #cart-block .cart-preview.active a,#cart-block.cart-white .cart-preview, #cart-block.cart-white .cart-preview.active a"
    },
    {
        "id": "header_6",
        "type": "color",
        "label": "Color hover Cart",
        "media": "@media (min-width: 992px)",
        "selector": "#cart-block .cart-preview.active a:hover,#cart-block.cart-white .cart-preview.active a:hover"
    },
    {
        "id": "header_7",
        "type": "color",
        "label": "Color Quantity Cart",
        "selector": "#cart-block .cart-products-count,#cart-block.cart-white .cart-products-count"
    },
    {
        "id": "header_8",
        "type": "color",
        "label": "Color hover Quantity Cart",
        "media": "@media (min-width: 992px)",
        "selector": "#cart-block .cart-preview.active a:hover .cart-products-count,#cart-block.cart-white .cart-preview.active a:hover .cart-products-count"
    },
    {
        "id": "header_9",
        "type": "background-color",
        "label": "Background color Quantity Cart",
        "selector": "#cart-block .cart-products-count,#cart-block.cart-white .cart-products-count"
    },
    {
        "id": "header_10",
        "type": "background-color",
        "label": "Background color hover Quantity Cart",
        "media": "@media (min-width: 992px)",
        "selector": "#cart-block .cart-preview.active a:hover .cart-products-count,#cart-block.cart-white .cart-preview.active a:hover .cart-products-count"
    },
    {
        "id": "header_11",
        "type": "color",
        "label": "Color link Menu",
        "media": "@media (min-width: 992px)",
        "selector": ".deo-horizontal-menu .megamenu > .nav-item > .nav-link,.menu-white .deo-horizontal-menu .megamenu > .nav-item > .nav-link,.menu-white.light .deo-horizontal-menu .megamenu > .nav-item > .nav-link"
    },
    {
        "id": "header_12",
        "type": "color",
        "label": "Color link hover Menu",
        "media": "@media (min-width: 992px)",
        "selector": ".deo-horizontal-menu .megamenu > .nav-item:hover > .nav-link, .deo-horizontal-menu .megamenu > .nav-item:focus > .nav-link,.menu-white .deo-horizontal-menu .megamenu > .nav-item:hover > .nav-link,.menu-white .deo-horizontal-menu .megamenu > .nav-item:focus > .nav-link,.menu-white.light .deo-horizontal-menu .megamenu > .nav-item:hover > .nav-link,.menu-white.light .deo-horizontal-menu .megamenu > .nav-item:focus > .nav-link"
    },
    {
        "id": "header_13",
        "type": "background-color",
        "label": "Background color Search",
        "selector": "#header .deo-search-advanced.search-bugi-one .popup-content"
    },
    {
        "id": "header_14",
        "type": "border-color",
        "label": "Border color Search",
        "selector": "#header .deo-search-advanced.search-bugi-one .popup-content,#header .deo-search-advanced.search-bugi-one .block_content .deo-advanced-search-top-button:before"
    },
    {
        "id": "header_15",
        "type": "color",
        "label": "Color Search",
        "selector": "#header .deo-search-advanced.search-bugi-one .block_content .deo-advanced-search-input .advanced_search_query,#header .deo-search-advanced.search-bugi-one .block_content .deo-advanced-search-input .advanced_search_query::-webkit-input-placeholder"
    },
    {
        "id": "header_16",
        "type": "color",
        "label": "Color button Search",
        "selector": "#header .deo-search-advanced.search-bugi-one .block_content .deo-advanced-search-top-button"
    },
    {
        "id": "header_17",
        "type": "color",
        "label": "Color hover button Search",
        "media": "@media (min-width: 992px)",
        "selector": "#header .deo-search-advanced.search-bugi-one .block_content .deo-advanced-search-top-button:hover"
    }
]